huaweicloudsdkces/__init__.py
huaweicloudsdkces/v1/__init__.py
huaweicloudsdkces/v1/ces_async_client.py
huaweicloudsdkces/v1/ces_client.py
huaweicloudsdkces/v1/model/__init__.py
huaweicloudsdkces/v1/model/additional_info_resp.py
huaweicloudsdkces/v1/model/alarm_action_enabled_resp.py
huaweicloudsdkces/v1/model/alarm_description.py
huaweicloudsdkces/v1/model/alarm_description_resp.py
huaweicloudsdkces/v1/model/alarm_enabled_resp.py
huaweicloudsdkces/v1/model/alarm_history_info_resp.py
huaweicloudsdkces/v1/model/alarm_level_resp.py
huaweicloudsdkces/v1/model/alarm_name.py
huaweicloudsdkces/v1/model/alarm_name_resp.py
huaweicloudsdkces/v1/model/alarm_rule_condition_resp.py
huaweicloudsdkces/v1/model/alarm_state_resp.py
huaweicloudsdkces/v1/model/alarm_template.py
huaweicloudsdkces/v1/model/alarm_template_condition.py
huaweicloudsdkces/v1/model/alarm_type_resp.py
huaweicloudsdkces/v1/model/batch_list_metric_data_request.py
huaweicloudsdkces/v1/model/batch_list_metric_data_request_body.py
huaweicloudsdkces/v1/model/batch_list_metric_data_response.py
huaweicloudsdkces/v1/model/batch_metric_data.py
huaweicloudsdkces/v1/model/batch_period.py
huaweicloudsdkces/v1/model/comparison_operator.py
huaweicloudsdkces/v1/model/comparison_operator_resp.py
huaweicloudsdkces/v1/model/condition.py
huaweicloudsdkces/v1/model/condition_resp.py
huaweicloudsdkces/v1/model/create_alarm_metric.py
huaweicloudsdkces/v1/model/create_alarm_request.py
huaweicloudsdkces/v1/model/create_alarm_request_body.py
huaweicloudsdkces/v1/model/create_alarm_response.py
huaweicloudsdkces/v1/model/create_alarm_template_request.py
huaweicloudsdkces/v1/model/create_alarm_template_request_body.py
huaweicloudsdkces/v1/model/create_alarm_template_response.py
huaweicloudsdkces/v1/model/create_events_request.py
huaweicloudsdkces/v1/model/create_events_request_body.py
huaweicloudsdkces/v1/model/create_events_response.py
huaweicloudsdkces/v1/model/create_metric_data_request.py
huaweicloudsdkces-3.1.184.dist-info/METADATA
huaweicloudsdkces-3.1.184.dist-info/WHEEL
huaweicloudsdkces-3.1.184.dist-info/licenses/LICENSE
huaweicloudsdkces-3.1.184.dist-info/RECORD
